{
    "culturecomponents": [
        {
            "image": "cultureimages/we-are-women.png",
            "title": "We Are Women",
            "description": "Interviews with four women about the complexity of womanhood and overcoming stereotypes and sexualization",
            "date": "Dec 7, 2022"
        },
        {
            "image": "cultureimages/exploitation-vs-exploration.jpeg",
            "title": "Exploitation vs. Exploration",
            "description": "The battling feminist perspectives on the porn industry",
            "date": "Dec 6, 2022"
        },
        {
            "image": "cultureimages/femininity-is-power.jpg",
            "title": "Femininity is Power",
            "description": "Exploring femininity’s role in the professional workplace",
            "date": "Dec 4, 2022"
        },
        {
            "image": "cultureimages/why-comply.png",
            "title": "Why Comply?",
            "description": "Empowering youth to combat outdated dress codes",
            "date": "Dec 3, 2022"
        },
        {
            "image": "cultureimages/shes-a-bitch.jpeg",
            "title": "She's a Bitch",
            "description": "Pathologizing and denying normative female emotions",
            "date": "Nov 30, 2022"
        },
        {
            "image": "",
            "title": "",
            "description": "",
            "date": ""
        },
        {
            "image": "",
            "title": "",
            "description": "",
            "date": ""
        },
        {
            "image": "",
            "title": "",
            "description": "",
            "date": ""
        },
        {
            "image": "",
            "title": "",
            "description": "",
            "date": ""
        },
        {
            "image": "",
            "title": "",
            "description": "",
            "date": ""
        },
        {
            "image": "",
            "title": "",
            "description": "",
            "date": ""
        },
        {
            "image": "",
            "title": "",
            "description": "",
            "date": ""
        },
        {
            "image": "",
            "title": "",
            "description": "",
            "date": ""
        },
        {
            "image": "",
            "title": "",
            "description": "",
            "date": ""
        },
        {
            "image": "",
            "title": "",
            "description": "",
            "date": ""
        },
        {
            "image": "",
            "title": "",
            "description": "",
            "date": ""
        },
        {
            "image": "",
            "title": "",
            "description": "",
            "date": ""
        },
        {
            "image": "",
            "title": "",
            "description": "",
            "date": ""
        },
        {
            "image": "",
            "title": "",
            "description": "",
            "date": ""
        },
        {
            "image": "",
            "title": "",
            "description": "",
            "date": ""
        },
        {
            "image": "",
            "title": "",
            "description": "",
            "date": ""
        },
        {
            "image": "",
            "title": "",
            "description": "",
            "date": ""
        },
        {
            "image": "",
            "title": "",
            "description": "",
            "date": ""
        },
        {
            "image": "",
            "title": "",
            "description": "",
            "date": ""
        },
        {
            "image": "",
            "title": "",
            "description": "",
            "date": ""
        },
        {
            "image": "",
            "title": "",
            "description": "",
            "date": ""
        },
        {
            "image": "",
            "title": "",
            "description": "",
            "date": ""
        },
        {
            "image": "",
            "title": "",
            "description": "",
            "date": ""
        },
        {
            "image": "",
            "title": "",
            "description": "",
            "date": ""
        },
        {
            "image": "",
            "title": "",
            "description": "",
            "date": ""
        }
    ]
}